{
  "minecraft:recipes/food/cooked_mutton_from_campfire_cooking": {
    "criteria": {
      "has_mutton": "2026-03-25 23:26:13 +0530"
    },
    "done": true
  },
  "minecraft:recipes/building_blocks/purple_wool": {
    "criteria": {
      "has_white_wool": "2026-03-25 23:26:13 +0530"
    },
    "done": true
  },
  "minecraft:recipes/building_blocks/lime_wool": {
    "criteria": {
      "has_white_wool": "2026-03-25 23:26:13 +0530"
    },
    "done": true
  },
  "minecraft:recipes/combat/iron_sword": {
    "criteria": {
      "has_iron_ingot": "2026-03-24 20:19:07 +0530"
    },
    "done": true
  },
  "minecraft:recipes/building_blocks/stone_bricks": {
    "criteria": {
      "has_stone": "2026-03-25 19:50:36 +0530"
    },
    "done": true
  },
  "minecraft:recipes/building_blocks/black_wool": {
    "criteria": {
      "has_white_wool": "2026-03-25 23:26:13 +0530"
    },
    "done": true
  },
  "minecraft:recipes/building_blocks/stone_bricks_from_stone_stonecutting": {
    "criteria": {
      "has_stone": "2026-03-25 19:50:36 +0530"
    },
    "done": true
  },
  "minecraft:recipes/combat/golden_chestplate": {
    "criteria": {
      "has_gold_ingot": "2026-03-24 20:19:07 +0530"
    },
    "done": true
  },
  "minecraft:recipes/decorations/white_bed": {
    "criteria": {
      "has_white_wool": "2026-03-25 23:26:13 +0530"
    },
    "done": true
  },
  "minecraft:recipes/building_blocks/green_wool": {
    "criteria": {
      "has_white_wool": "2026-03-25 23:26:13 +0530"
    },
    "done": true
  },
  "minecraft:recipes/tools/diamond_axe": {
    "criteria": {
      "has_diamond": "2026-03-24 20:19:08 +0530"
    },
    "done": true
  },
  "minecraft:recipes/tools/iron_pickaxe": {
    "criteria": {
      "has_iron_ingot": "2026-03-24 20:19:07 +0530"
    },
    "done": true
  },
  "minecraft:recipes/building_blocks/brown_wool": {
    "criteria": {
      "has_white_wool": "2026-03-25 23:26:13 +0530"
    },
    "done": true
  },
  "minecraft:recipes/building_blocks/magenta_wool": {
    "criteria": {
      "has_white_wool": "2026-03-25 23:26:13 +0530"
    },
    "done": true
  },
  "minecraft:recipes/redstone/redstone": {
    "criteria": {
      "has_redstone_block": "2026-04-02 08:03:04 +0530"
    },
    "done": true
  },
  "minecraft:recipes/tools/golden_hoe": {
    "criteria": {
      "has_gold_ingot": "2026-03-24 20:19:07 +0530"
    },
    "done": true
  },
  "minecraft:recipes/food/bread": {
    "criteria": {
      "has_wheat": "2026-03-25 23:24:32 +0530"
    },
    "done": true
  },
  "minecraft:recipes/building_blocks/smooth_stone": {
    "criteria": {
      "has_stone": "2026-03-25 19:50:36 +0530"
    },
    "done": true
  },
  "minecraft:recipes/misc/iron_nugget": {
    "criteria": {
      "has_iron_ingot": "2026-03-24 20:19:07 +0530"
    },
    "done": true
  },
  "minecraft:recipes/decorations/chest": {
    "criteria": {
      "has_lots_of_items": "2026-03-19 12:47:20 +0530"
    },
    "done": true
  },
  "minecraft:story/shiny_gear": {
    "criteria": {
      "diamond_boots": "2026-03-24 20:16:25 +0530"
    },
    "done": true
  },
  "minecraft:recipes/combat/golden_sword": {
    "criteria": {
      "has_gold_ingot": "2026-03-24 20:19:07 +0530"
    },
    "done": true
  },
  "minecraft:recipes/building_blocks/stone_slab_from_stone_stonecutting": {
    "criteria": {
      "has_stone": "2026-03-25 19:50:36 +0530"
    },
    "done": true
  },
  "minecraft:recipes/building_blocks/iron_block": {
    "criteria": {
      "has_iron_ingot": "2026-03-24 20:19:07 +0530"
    },
    "done": true
  },
  "minecraft:recipes/building_blocks/chiseled_stone_bricks_stone_from_stonecutting": {
    "criteria": {
      "has_stone": "2026-03-25 19:50:36 +0530"
    },
    "done": true
  },
  "minecraft:recipes/decorations/painting": {
    "criteria": {
      "has_wool": "2026-03-25 23:26:13 +0530"
    },
    "done": true
  },
  "minecraft:recipes/combat/diamond_sword": {
    "criteria": {
      "has_diamond": "2026-03-24 20:19:08 +0530"
    },
    "done": true
  },
  "minecraft:recipes/building_blocks/cyan_wool": {
    "criteria": {
      "has_white_wool": "2026-03-25 23:26:13 +0530"
    },
    "done": true
  },
  "minecraft:recipes/tools/shears": {
    "criteria": {
      "has_iron_ingot": "2026-03-24 20:19:07 +0530"
    },
    "done": true
  },
  "minecraft:recipes/building_blocks/stone_slab": {
    "criteria": {
      "has_stone": "2026-03-25 19:50:36 +0530"
    },
    "done": true
  },
  "minecraft:recipes/decorations/black_carpet": {
    "criteria": {
      "has_black_wool": "2026-03-25 23:26:13 +0530"
    },
    "done": true
  },
  "minecraft:recipes/building_blocks/stone_brick_slab_from_stone_stonecutting": {
    "criteria": {
      "has_stone": "2026-03-25 19:50:36 +0530"
    },
    "done": true
  },
  "buildscape:recipes/buildscape/vertical_hay_bale_slab_from_slab_stonecutting": {
    "criteria": {
      "has_hay_bale_slab": "2026-03-24 19:12:50 +0530"
    },
    "done": true
  },
  "minecraft:recipes/redstone/light_weighted_pressure_plate": {
    "criteria": {
      "has_gold_ingot": "2026-03-24 20:19:07 +0530"
    },
    "done": true
  },
  "minecraft:recipes/decorations/jukebox": {
    "criteria": {
      "has_diamond": "2026-03-24 20:19:08 +0530"
    },
    "done": true
  },
  "minecraft:recipes/transportation/spruce_boat": {
    "criteria": {
      "in_water": "2026-03-25 23:11:46 +0530"
    },
    "done": true
  },
  "minecraft:recipes/building_blocks/waxed_oxidized_cut_copper_stairs_from_honeycomb": {
    "criteria": {
      "has_oxidized_cut_copper_stairs": "2026-03-19 16:48:40 +0530"
    },
    "done": true
  },
  "minecraft:recipes/building_blocks/light_blue_wool": {
    "criteria": {
      "has_white_wool": "2026-03-25 23:26:13 +0530"
    },
    "done": true
  },
  "minecraft:recipes/redstone/dispenser": {
    "criteria": {
      "has_bow": "2026-03-22 08:22:19 +0530"
    },
    "done": true
  },
  "buildscape:recipes/buildscape/vertical_stripped_bamboo_block_slab_from_slab_stonecutting": {
    "criteria": {
      "has_stripped_bamboo_block_slab": "2026-03-25 22:44:27 +0530"
    },
    "done": true
  },
  "minecraft:recipes/building_blocks/gray_wool": {
    "criteria": {
      "has_white_wool": "2026-03-25 23:26:13 +0530"
    },
    "done": true
  },
  "minecraft:recipes/misc/gold_nugget": {
    "criteria": {
      "has_gold_ingot": "2026-03-24 20:19:07 +0530"
    },
    "done": true
  },
  "minecraft:recipes/combat/iron_leggings": {
    "criteria": {
      "has_iron_ingot": "2026-03-24 20:19:07 +0530"
    },
    "done": true
  },
  "minecraft:recipes/tools/golden_axe": {
    "criteria": {
      "has_gold_ingot": "2026-03-24 20:19:07 +0530"
    },
    "done": true
  },
  "minecraft:recipes/tools/iron_axe": {
    "criteria": {
      "has_iron_ingot": "2026-03-24 20:19:07 +0530"
    },
    "done": true
  },
  "minecraft:recipes/combat/shield": {
    "criteria": {
      "has_iron_ingot": "2026-03-24 20:19:07 +0530"
    },
    "done": true
  },
  "minecraft:recipes/decorations/brown_banner": {
    "criteria": {
      "has_brown_wool": "2026-03-25 23:26:13 +0530"
    },
    "done": true
  },
  "minecraft:recipes/combat/golden_helmet": {
    "criteria": {
      "has_gold_ingot": "2026-03-24 20:19:07 +0530"
    },
    "done": true
  },
  "minecraft:recipes/decorations/black_banner": {
    "criteria": {
      "has_black_wool": "2026-03-25 23:26:13 +0530"
    },
    "done": true
  },
  "minecraft:recipes/misc/bucket": {
    "criteria": {
      "has_iron_ingot": "2026-03-24 20:19:07 +0530"
    },
    "done": true
  },
  "minecraft:recipes/combat/iron_boots": {
    "criteria": {
      "has_iron_ingot": "2026-03-24 20:19:07 +0530"
    },
    "done": true
  },
  "minecraft:recipes/redstone/hopper": {
    "criteria": {
      "has_iron_ingot": "2026-03-24 20:19:07 +0530"
    },
    "done": true
  },
  "minecraft:story/iron_tools": {
    "criteria": {
      "iron_pickaxe": "2026-03-21 18:58:16 +0530"
    },
    "done": true
  },
  "minecraft:recipes/redstone/stone_button": {
    "criteria": {
      "has_stone": "2026-03-25 19:50:36 +0530"
    },
    "done": true
  },
  "minecraft:recipes/decorations/white_banner": {
    "criteria": {
      "has_white_wool": "2026-03-25 23:26:13 +0530"
    },
    "done": true
  },
  "minecraft:recipes/combat/iron_chestplate": {
    "criteria": {
      "has_iron_ingot": "2026-03-24 20:19:07 +0530"
    },
    "done": true
  },
  "minecraft:recipes/combat/crossbow": {
    "criteria": {
      "has_iron_ingot": "2026-03-24 20:19:07 +0530"
    },
    "done": true
  },
  "minecraft:recipes/building_blocks/yellow_wool": {
    "criteria": {
      "has_white_wool": "2026-03-25 23:26:13 +0530"
    },
    "done": true
  },
  "minecraft:recipes/building_blocks/hay_block": {
    "criteria": {
      "has_wheat": "2026-03-25 23:24:32 +0530"
    },
    "done": true
  },
  "minecraft:recipes/combat/iron_helmet": {
    "criteria": {
      "has_iron_ingot": "2026-03-24 20:19:07 +0530"
    },
    "done": true
  },
  "minecraft:recipes/tools/golden_shovel": {
    "criteria": {
      "has_gold_ingot": "2026-03-24 20:19:07 +0530"
    },
    "done": true
  },
  "minecraft:recipes/misc/iron_nugget_from_blasting": {
    "criteria": {
      "has_iron_pickaxe": "2026-03-21 18:58:16 +0530"
    },
    "done": true
  },
  "minecraft:adventure/kill_a_mob": {
    "criteria": {
      "minecraft:slime": "2026-03-22 16:41:50 +0530"
    },
    "done": true
  },
  "minecraft:recipes/building_blocks/stone_stairs_from_stone_stonecutting": {
    "criteria": {
      "has_stone": "2026-03-25 19:50:36 +0530"
    },
    "done": true
  },
  "buildscape:recipes/buildscape/vertical_cut_steel_slab_from_slab_stonecutting": {
    "criteria": {
      "has_cut_steel_slab": "2026-03-25 18:27:25 +0530"
    },
    "done": true
  },
  "minecraft:recipes/decorations/iron_bars": {
    "criteria": {
      "has_iron_ingot": "2026-03-24 20:19:07 +0530"
    },
    "done": true
  },
  "minecraft:recipes/tools/golden_pickaxe": {
    "criteria": {
      "has_gold_ingot": "2026-03-24 20:19:07 +0530"
    },
    "done": true
  },
  "buildscape:recipes/buildscape/vertical_bamboo_block_slab_from_slab_stonecutting": {
    "criteria": {
      "has_bamboo_block_slab": "2026-03-25 22:44:30 +0530"
    },
    "done": true
  },
  "minecraft:recipes/building_blocks/gold_block": {
    "criteria": {
      "has_gold_ingot": "2026-03-24 20:19:07 +0530"
    },
    "done": true
  },
  "minecraft:recipes/building_blocks/blue_wool": {
    "criteria": {
      "has_white_wool": "2026-03-25 23:26:13 +0530"
    },
    "done": true
  },
  "minecraft:recipes/combat/diamond_chestplate": {
    "criteria": {
      "has_diamond": "2026-03-24 20:19:08 +0530"
    },
    "done": true
  },
  "buildscape:recipes/buildscape/vertical_blue_sandstone_slab_from_slab_stonecutting": {
    "criteria": {
      "has_blue_sandstone_slab": "2026-03-19 11:36:56 +0530"
    },
    "done": true
  },
  "minecraft:recipes/transportation/minecart": {
    "criteria": {
      "has_iron_ingot": "2026-03-24 20:19:07 +0530"
    },
    "done": true
  },
  "minecraft:recipes/decorations/stonecutter": {
    "criteria": {
      "has_stone": "2026-03-25 19:50:36 +0530"
    },
    "done": true
  },
  "minecraft:recipes/brewing/cauldron": {
    "criteria": {
      "has_water_bucket": "2026-03-24 19:16:55 +0530"
    },
    "done": true
  },
  "minecraft:adventure/adventuring_time": {
    "criteria": {
      "minecraft:plains": "2026-03-19 11:36:56 +0530"
    },
    "done": false
  },
  "minecraft:recipes/redstone/iron_door": {
    "criteria": {
      "has_iron_ingot": "2026-03-24 20:19:07 +0530"
    },
    "done": true
  },
  "minecraft:recipes/combat/diamond_leggings": {
    "criteria": {
      "has_diamond": "2026-03-24 20:19:08 +0530"
    },
    "done": true
  },
  "minecraft:recipes/building_blocks/orange_wool": {
    "criteria": {
      "has_white_wool": "2026-03-25 23:26:13 +0530"
    },
    "done": true
  },
  "minecraft:recipes/tools/iron_hoe": {
    "criteria": {
      "has_iron_ingot": "2026-03-24 20:19:07 +0530"
    },
    "done": true
  },
  "minecraft:recipes/transportation/birch_boat": {
    "criteria": {
      "in_water": "2026-03-25 23:11:46 +0530"
    },
    "done": true
  },
  "minecraft:recipes/food/golden_apple": {
    "criteria": {
      "has_gold_ingot": "2026-03-24 20:19:07 +0530"
    },
    "done": true
  },
  "minecraft:recipes/tools/iron_shovel": {
    "criteria": {
      "has_iron_ingot": "2026-03-24 20:19:07 +0530"
    },
    "done": true
  },
  "minecraft:recipes/transportation/acacia_boat": {
    "criteria": {
      "in_water": "2026-03-25 23:11:46 +0530"
    },
    "done": true
  },
  "minecraft:recipes/redstone/iron_trapdoor": {
    "criteria": {
      "has_iron_ingot": "2026-03-24 20:19:07 +0530"
    },
    "done": true
  },
  "minecraft:recipes/decorations/smithing_table": {
    "criteria": {
      "has_iron_ingot": "2026-03-24 20:19:07 +0530"
    },
    "done": true
  },
  "minecraft:adventure/root": {
    "criteria": {
      "killed_by_something": "2026-03-22 16:40:20 +0530"
    },
    "done": true
  },
  "minecraft:recipes/redstone/stone_pressure_plate": {
    "criteria": {
      "has_stone": "2026-03-25 19:50:36 +0530"
    },
    "done": true
  },
  "minecraft:recipes/transportation/jungle_boat": {
    "criteria": {
      "in_water": "2026-03-25 23:11:46 +0530"
    },
    "done": true
  },
  "minecraft:recipes/decorations/black_bed": {
    "criteria": {
      "has_black_wool": "2026-03-25 23:26:13 +0530"
    },
    "done": true
  },
  "minecraft:nether/netherite_armor": {
    "criteria": {
      "netherite_armor": "2026-03-22 15:07:19 +0530"
    },
    "done": true
  },
  "minecraft:recipes/decorations/stone_brick_walls_from_stone_stonecutting": {
    "criteria": {
      "has_stone": "2026-03-25 19:50:36 +0530"
    },
    "done": true
  },
  "minecraft:recipes/decorations/brown_carpet": {
    "criteria": {
      "has_brown_wool": "2026-03-25 23:26:13 +0530"
    },
    "done": true
  },
  "minecraft:recipes/building_blocks/stone_brick_stairs_from_stone_stonecutting": {
    "criteria": {
      "has_stone": "2026-03-25 19:50:36 +0530"
    },
    "done": true
  },
  "minecraft:recipes/redstone/heavy_weighted_pressure_plate": {
    "criteria": {
      "has_iron_ingot": "2026-03-24 20:19:07 +0530"
    },
    "done": true
  },
  "minecraft:recipes/building_blocks/diamond_block": {
    "criteria": {
      "has_diamond": "2026-03-24 20:19:08 +0530"
    },
    "done": true
  },
  "minecraft:recipes/transportation/dark_oak_boat": {
    "criteria": {
      "in_water": "2026-03-25 23:11:46 +0530"
    },
    "done": true
  },
  "minecraft:recipes/tools/diamond_pickaxe": {
    "criteria": {
      "has_diamond": "2026-03-24 20:19:08 +0530"
    },
    "done": true
  },
  "minecraft:recipes/tools/diamond_hoe": {
    "criteria": {
      "has_diamond": "2026-03-24 20:19:08 +0530"
    },
    "done": true
  },
  "minecraft:recipes/building_blocks/pink_wool": {
    "criteria": {
      "has_white_wool": "2026-03-25 23:26:13 +0530"
    },
    "done": true
  },
  "minecraft:adventure/kill_all_mobs": {
    "criteria": {
      "minecraft:slime": "2026-03-22 16:41:50 +0530"
    },
    "done": false
  },
  "minecraft:recipes/tools/diamond_shovel": {
    "criteria": {
      "has_diamond": "2026-03-24 20:19:08 +0530"
    },
    "done": true
  },
  "minecraft:recipes/combat/golden_leggings": {
    "criteria": {
      "has_gold_ingot": "2026-03-24 20:19:07 +0530"
    },
    "done": true
  },
  "minecraft:recipes/decorations/lantern": {
    "criteria": {
      "has_iron_ingot": "2026-03-24 20:19:07 +0530"
    },
    "done": true
  },
  "minecraft:recipes/decorations/white_carpet": {
    "criteria": {
      "has_white_wool": "2026-03-25 23:26:13 +0530"
    },
    "done": true
  },
  "minecraft:recipes/building_blocks/stone_stairs": {
    "criteria": {
      "has_stone": "2026-03-25 19:50:36 +0530"
    },
    "done": true
  },
  "minecraft:recipes/decorations/brown_bed": {
    "criteria": {
      "has_brown_wool": "2026-03-25 23:26:13 +0530"
    },
    "done": true
  },
  "minecraft:recipes/misc/iron_nugget_from_smelting": {
    "criteria": {
      "has_iron_pickaxe": "2026-03-21 18:58:16 +0530"
    },
    "done": true
  },
  "minecraft:recipes/food/cooked_mutton_from_smoking": {
    "criteria": {
      "has_mutton": "2026-03-25 23:26:13 +0530"
    },
    "done": true
  },
  "minecraft:recipes/decorations/chain": {
    "criteria": {
      "has_iron_ingot": "2026-03-24 20:19:07 +0530"
    },
    "done": true
  },
  "minecraft:recipes/combat/diamond_boots": {
    "criteria": {
      "has_diamond": "2026-03-24 20:19:08 +0530"
    },
    "done": true
  },
  "minecraft:story/mine_diamond": {
    "criteria": {
      "diamond": "2026-03-24 20:19:08 +0530"
    },
    "done": true
  },
  "minecraft:recipes/combat/diamond_helmet": {
    "criteria": {
      "has_diamond": "2026-03-24 20:19:08 +0530"
    },
    "done": true
  },
  "minecraft:recipes/building_blocks/light_gray_wool": {
    "criteria": {
      "has_white_wool": "2026-03-25 23:26:13 +0530"
    },
    "done": true
  },
  "minecraft:recipes/building_blocks/red_wool": {
    "criteria": {
      "has_white_wool": "2026-03-25 23:26:13 +0530"
    },
    "done": true
  },
  "minecraft:recipes/transportation/oak_boat": {
    "criteria": {
      "in_water": "2026-03-25 23:11:46 +0530"
    },
    "done": true
  },
  "minecraft:story/smelt_iron": {
    "criteria": {
      "iron": "2026-03-24 20:19:07 +0530"
    },
    "done": true
  },
  "minecraft:recipes/food/cooked_mutton": {
    "criteria": {
      "has_mutton": "2026-03-25 23:26:13 +0530"
    },
    "done": true
  },
  "minecraft:recipes/combat/golden_boots": {
    "criteria": {
      "has_gold_ingot": "2026-03-24 20:19:07 +0530"
    },
    "done": true
  },
  "DataVersion": 2975
}